bin/convert_hf_to_gguf.py
bin/ggml-metal.metal
bin/llama-llava-cli
bin/llama-minicpmv-cli
include/ggml-alloc.h
include/ggml-backend.h
include/ggml-blas.h
include/ggml-cann.h
include/ggml-cuda.h
include/ggml-kompute.h
include/ggml-metal.h
include/ggml-rpc.h
include/ggml-sycl.h
include/ggml-vulkan.h
include/ggml.h
include/llama.h
lib/cmake/llama/llama-config.cmake
lib/cmake/llama/llama-version.cmake
lib/libggml.a
lib/libggml_llama.dylib
lib/libllama.dylib
lib/libllava.dylib
lib/pkgconfig/llama.pc
nexa/gguf/lib/libggml_llama.dylib
nexa/gguf/lib/libllama.dylib
nexa/gguf/lib/libllava.dylib
nexa/gguf/lib/libstable-diffusion.dylib
nexai-0.0.0.dev0.dist-info/METADATA
nexai-0.0.0.dev0.dist-info/WHEEL
nexai-0.0.0.dev0.dist-info/entry_points.txt
nexai-0.0.0.dev0.dist-info/licenses/LICENSE
nexai-0.0.0.dev0.dist-info/RECORD
