Metadata-Version: 2.1
Name: nexai
Version: 0.0.0.dev0
Summary: Nexa AI SDK
Author-Email: Nexa AI <octopus@nexa4ai.com>
License: MIT
Classifier: Programming Language :: Python :: 3
Classifier: Programming Language :: Python :: 3.8
Classifier: Programming Language :: Python :: 3.9
Classifier: Programming Language :: Python :: 3.10
Classifier: Programming Language :: Python :: 3.11
Classifier: Programming Language :: Python :: 3.12
Project-URL: Homepage, https://github.com/NexaAI/nexa-sdk
Project-URL: Issues, https://github.com/NexaAI/nexa-sdk/issues
Project-URL: Documentation, https://docs-test.nexa4ai.com/
Requires-Python: >=3.7
Requires-Dist: typing-extensions>=4.5.0
Requires-Dist: numpy>=1.20.0
Requires-Dist: diskcache>=5.6.1
Requires-Dist: jinja2>=2.11.3
Requires-Dist: librosa>=0.8.0
Requires-Dist: boto3>=1.34.148
Requires-Dist: botocore>=1.34.148
Requires-Dist: fastapi
Requires-Dist: uvicorn
Requires-Dist: sse-starlette
Requires-Dist: pydantic-settings
Requires-Dist: diskcache
Requires-Dist: starlette_context
Requires-Dist: pillow
Requires-Dist: streamlit
Requires-Dist: tqdm
Requires-Dist: tabulate
Requires-Dist: faster_whisper
